{"skeleton":{"hash":"VsNIJ8eVzvG4P9mC7ASERCnu4dA","spine":"3.6.53","width":1060,"height":1840,"images":"../texiao/"},"bones":[{"name":"root"},{"name":"zong","parent":"root"},{"name":"0","parent":"zong","x":-5.98,"y":-444.54,"scaleX":1.415,"scaleY":1.415},{"name":"1","parent":"zong","x":-209.12,"y":-451.71,"scaleX":0.968,"scaleY":0.968},{"name":"2","parent":"0","x":6.75,"y":-27.31},{"name":"3","parent":"1","x":6.75,"y":-27.31},{"name":"4","parent":"zong","x":204.34,"y":-451.71,"scaleX":0.928,"scaleY":0.928},{"name":"5","parent":"4","x":6.75,"y":-27.31},{"name":"g2","parent":"2"},{"name":"g3","parent":"3"},{"name":"g4","parent":"5"},{"name":"shikuai2","parent":"0","x":-6.25,"y":-61.31},{"name":"shikuai3","parent":"1","x":-6.25,"y":-61.31},{"name":"shikuai4","parent":"4","x":-6.25,"y":-61.31}],"slots":[{"name":"base_1","bone":"root"},{"name":"mb","bone":"zong","attachment":"mb"},{"name":"shikuai2","bone":"shikuai2"},{"name":"shikuai3","bone":"shikuai3"},{"name":"shikuai4","bone":"shikuai4"},{"name":"g2","bone":"g2","blend":"additive"},{"name":"g3","bone":"g3","blend":"additive"},{"name":"g4","bone":"g4","blend":"additive"}],"skins":{"default":{"g2":{"g":{"width":345,"height":300}},"g3":{"g":{"width":345,"height":300}},"g4":{"g":{"width":345,"height":300}},"mb":{"mb":{"type":"clipping","end":"mb","vertexCount":4,"vertices":[318.56,-450.17,-321.84,-450.17,-321.84,-91.07,322.55,-89.74],"color":"ce3a3aff"}},"shikuai2":{"shikuai_0":{"x":-11,"y":167,"width":429,"height":414},"shikuai_1":{"x":-11,"y":167,"width":429,"height":414},"shikuai_2":{"x":-11,"y":167,"width":429,"height":414},"shikuai_3":{"x":-11,"y":167,"width":429,"height":414},"shikuai_4":{"x":-11,"y":167,"width":429,"height":414},"shikuai_5":{"x":-11,"y":167,"width":429,"height":414},"shikuai_6":{"x":-11,"y":167,"width":429,"height":414},"shikuai_7":{"x":-11,"y":167,"width":429,"height":414},"shikuai_8":{"x":-11,"y":167,"width":429,"height":414},"shikuai_9":{"x":-11,"y":167,"width":429,"height":414},"shikuai_10":{"x":-11,"y":167,"width":429,"height":414},"shikuai_11":{"x":-11,"y":167,"width":429,"height":414},"shikuai_12":{"x":-11,"y":167,"width":429,"height":414},"shikuai_13":{"x":-11,"y":167,"width":429,"height":414},"shikuai_14":{"x":-11,"y":167,"width":429,"height":414}},"shikuai3":{"shikuai_0":{"x":-11,"y":167,"width":429,"height":414},"shikuai_1":{"x":-11,"y":167,"width":429,"height":414},"shikuai_2":{"x":-11,"y":167,"width":429,"height":414},"shikuai_3":{"x":-11,"y":167,"width":429,"height":414},"shikuai_4":{"x":-11,"y":167,"width":429,"height":414},"shikuai_5":{"x":-11,"y":167,"width":429,"height":414},"shikuai_6":{"x":-11,"y":167,"width":429,"height":414},"shikuai_7":{"x":-11,"y":167,"width":429,"height":414},"shikuai_8":{"x":-11,"y":167,"width":429,"height":414},"shikuai_9":{"x":-11,"y":167,"width":429,"height":414},"shikuai_10":{"x":-11,"y":167,"width":429,"height":414},"shikuai_11":{"x":-11,"y":167,"width":429,"height":414},"shikuai_12":{"x":-11,"y":167,"width":429,"height":414},"shikuai_13":{"x":-11,"y":167,"width":429,"height":414},"shikuai_14":{"x":-11,"y":167,"width":429,"height":414}},"shikuai4":{"shikuai_0":{"x":-11,"y":167,"width":429,"height":414},"shikuai_1":{"x":-11,"y":167,"width":429,"height":414},"shikuai_2":{"x":-11,"y":167,"width":429,"height":414},"shikuai_3":{"x":-11,"y":167,"width":429,"height":414},"shikuai_4":{"x":-11,"y":167,"width":429,"height":414},"shikuai_5":{"x":-11,"y":167,"width":429,"height":414},"shikuai_6":{"x":-11,"y":167,"width":429,"height":414},"shikuai_7":{"x":-11,"y":167,"width":429,"height":414},"shikuai_8":{"x":-11,"y":167,"width":429,"height":414},"shikuai_9":{"x":-11,"y":167,"width":429,"height":414},"shikuai_10":{"x":-11,"y":167,"width":429,"height":414},"shikuai_11":{"x":-11,"y":167,"width":429,"height":414},"shikuai_12":{"x":-11,"y":167,"width":429,"height":414},"shikuai_13":{"x":-11,"y":167,"width":429,"height":414},"shikuai_14":{"x":-11,"y":167,"width":429,"height":414}}}},"animations":{"animation":{"slots":{"g2":{"color":[{"time":0,"color":"ffffff00","curve":[0.25,0,0.75,1]},{"time":0.1667,"color":"ffffffff","curve":[0.25,0,0.625,0.5]},{"time":1,"color":"ffffff7a","curve":[0.375,0.5,0.75,1]},{"time":1.5,"color":"ffffff85","curve":[0.25,0,0.75,1]},{"time":2,"color":"ffffff00"}],"attachment":[{"time":0,"name":"g"}]},"g3":{"color":[{"time":0,"color":"ffffff00","curve":[0.25,0,0.75,1]},{"time":0.1667,"color":"ffffffff","curve":[0.25,0,0.625,0.5]},{"time":1,"color":"ffffff7a","curve":[0.375,0.5,0.75,1]},{"time":1.5,"color":"ffffff85","curve":[0.25,0,0.75,1]},{"time":2,"color":"ffffff00"}],"attachment":[{"time":0,"name":"g"}]},"g4":{"color":[{"time":0,"color":"ffffff00","curve":[0.25,0,0.75,1]},{"time":0.1667,"color":"ffffffff","curve":[0.25,0,0.625,0.5]},{"time":1,"color":"ffffff7a","curve":[0.375,0.5,0.75,1]},{"time":1.5,"color":"ffffff85","curve":[0.25,0,0.75,1]},{"time":2,"color":"ffffff00"}],"attachment":[{"time":0,"name":"g"}]},"shikuai2":{"color":[{"time":0,"color":"ffffff00","curve":[0.25,0,0.75,1]},{"time":0.1667,"color":"ffffffff","curve":"stepped"},{"time":1.8333,"color":"ffffffff","curve":[0.25,0,0.75,1]},{"time":2,"color":"ffffff00"}],"attachment":[{"time":0,"name":"shikuai_0"},{"time":0.0333,"name":"shikuai_1"},{"time":0.0667,"name":"shikuai_2"},{"time":0.1,"name":"shikuai_3"},{"time":0.1333,"name":"shikuai_4"},{"time":0.1667,"name":"shikuai_5"},{"time":0.2,"name":"shikuai_6"},{"time":0.2333,"name":"shikuai_7"},{"time":0.2667,"name":"shikuai_8"},{"time":0.3,"name":"shikuai_9"},{"time":0.3333,"name":"shikuai_10"},{"time":0.3667,"name":"shikuai_11"},{"time":0.4,"name":"shikuai_12"},{"time":0.4333,"name":"shikuai_13"},{"time":0.4667,"name":"shikuai_14"},{"time":0.5,"name":"shikuai_0"},{"time":0.5333,"name":"shikuai_1"},{"time":0.5667,"name":"shikuai_2"},{"time":0.6,"name":"shikuai_3"},{"time":0.6333,"name":"shikuai_4"},{"time":0.6667,"name":"shikuai_5"},{"time":0.7,"name":"shikuai_6"},{"time":0.7333,"name":"shikuai_7"},{"time":0.7667,"name":"shikuai_8"},{"time":0.8,"name":"shikuai_9"},{"time":0.8333,"name":"shikuai_10"},{"time":0.8667,"name":"shikuai_11"},{"time":0.9,"name":"shikuai_12"},{"time":0.9333,"name":"shikuai_13"},{"time":0.9667,"name":"shikuai_14"},{"time":1,"name":"shikuai_0"},{"time":1.0333,"name":"shikuai_1"},{"time":1.0667,"name":"shikuai_2"},{"time":1.1,"name":"shikuai_3"},{"time":1.1333,"name":"shikuai_4"},{"time":1.1667,"name":"shikuai_5"},{"time":1.2,"name":"shikuai_6"},{"time":1.2333,"name":"shikuai_7"},{"time":1.2667,"name":"shikuai_8"},{"time":1.3,"name":"shikuai_9"},{"time":1.3333,"name":"shikuai_10"},{"time":1.3667,"name":"shikuai_11"},{"time":1.4,"name":"shikuai_12"},{"time":1.4333,"name":"shikuai_13"},{"time":1.4667,"name":"shikuai_14"},{"time":1.5,"name":"shikuai_0"},{"time":1.5333,"name":"shikuai_1"},{"time":1.5667,"name":"shikuai_2"},{"time":1.6,"name":"shikuai_3"},{"time":1.6333,"name":"shikuai_4"},{"time":1.6667,"name":"shikuai_5"},{"time":1.7,"name":"shikuai_6"},{"time":1.7333,"name":"shikuai_7"},{"time":1.7667,"name":"shikuai_8"},{"time":1.8,"name":"shikuai_9"},{"time":1.8333,"name":"shikuai_10"},{"time":1.8667,"name":"shikuai_11"},{"time":1.9,"name":"shikuai_12"},{"time":1.9333,"name":"shikuai_13"},{"time":1.9667,"name":"shikuai_14"}]},"shikuai3":{"color":[{"time":0,"color":"ffffff00","curve":[0.25,0,0.75,1]},{"time":0.1667,"color":"ffffffff","curve":"stepped"},{"time":1.8333,"color":"ffffffff","curve":[0.25,0,0.75,1]},{"time":2,"color":"ffffff00"}],"attachment":[{"time":0,"name":"shikuai_0"},{"time":0.0333,"name":"shikuai_1"},{"time":0.0667,"name":"shikuai_2"},{"time":0.1,"name":"shikuai_3"},{"time":0.1333,"name":"shikuai_4"},{"time":0.1667,"name":"shikuai_5"},{"time":0.2,"name":"shikuai_6"},{"time":0.2333,"name":"shikuai_7"},{"time":0.2667,"name":"shikuai_8"},{"time":0.3,"name":"shikuai_9"},{"time":0.3333,"name":"shikuai_10"},{"time":0.3667,"name":"shikuai_11"},{"time":0.4,"name":"shikuai_12"},{"time":0.4333,"name":"shikuai_13"},{"time":0.4667,"name":"shikuai_14"},{"time":0.5,"name":"shikuai_0"},{"time":0.5333,"name":"shikuai_1"},{"time":0.5667,"name":"shikuai_2"},{"time":0.6,"name":"shikuai_3"},{"time":0.6333,"name":"shikuai_4"},{"time":0.6667,"name":"shikuai_5"},{"time":0.7,"name":"shikuai_6"},{"time":0.7333,"name":"shikuai_7"},{"time":0.7667,"name":"shikuai_8"},{"time":0.8,"name":"shikuai_9"},{"time":0.8333,"name":"shikuai_10"},{"time":0.8667,"name":"shikuai_11"},{"time":0.9,"name":"shikuai_12"},{"time":0.9333,"name":"shikuai_13"},{"time":0.9667,"name":"shikuai_14"},{"time":1,"name":"shikuai_0"},{"time":1.0333,"name":"shikuai_1"},{"time":1.0667,"name":"shikuai_2"},{"time":1.1,"name":"shikuai_3"},{"time":1.1333,"name":"shikuai_4"},{"time":1.1667,"name":"shikuai_5"},{"time":1.2,"name":"shikuai_6"},{"time":1.2333,"name":"shikuai_7"},{"time":1.2667,"name":"shikuai_8"},{"time":1.3,"name":"shikuai_9"},{"time":1.3333,"name":"shikuai_10"},{"time":1.3667,"name":"shikuai_11"},{"time":1.4,"name":"shikuai_12"},{"time":1.4333,"name":"shikuai_13"},{"time":1.4667,"name":"shikuai_14"},{"time":1.5,"name":"shikuai_0"},{"time":1.5333,"name":"shikuai_1"},{"time":1.5667,"name":"shikuai_2"},{"time":1.6,"name":"shikuai_3"},{"time":1.6333,"name":"shikuai_4"},{"time":1.6667,"name":"shikuai_5"},{"time":1.7,"name":"shikuai_6"},{"time":1.7333,"name":"shikuai_7"},{"time":1.7667,"name":"shikuai_8"},{"time":1.8,"name":"shikuai_9"},{"time":1.8333,"name":"shikuai_10"},{"time":1.8667,"name":"shikuai_11"},{"time":1.9,"name":"shikuai_12"},{"time":1.9333,"name":"shikuai_13"},{"time":1.9667,"name":"shikuai_14"}]},"shikuai4":{"color":[{"time":0,"color":"ffffff00","curve":[0.25,0,0.75,1]},{"time":0.1667,"color":"ffffffff","curve":"stepped"},{"time":1.8333,"color":"ffffffff","curve":[0.25,0,0.75,1]},{"time":2,"color":"ffffff00"}],"attachment":[{"time":0,"name":"shikuai_0"},{"time":0.0333,"name":"shikuai_1"},{"time":0.0667,"name":"shikuai_2"},{"time":0.1,"name":"shikuai_3"},{"time":0.1333,"name":"shikuai_4"},{"time":0.1667,"name":"shikuai_5"},{"time":0.2,"name":"shikuai_6"},{"time":0.2333,"name":"shikuai_7"},{"time":0.2667,"name":"shikuai_8"},{"time":0.3,"name":"shikuai_9"},{"time":0.3333,"name":"shikuai_10"},{"time":0.3667,"name":"shikuai_11"},{"time":0.4,"name":"shikuai_12"},{"time":0.4333,"name":"shikuai_13"},{"time":0.4667,"name":"shikuai_14"},{"time":0.5,"name":"shikuai_0"},{"time":0.5333,"name":"shikuai_1"},{"time":0.5667,"name":"shikuai_2"},{"time":0.6,"name":"shikuai_3"},{"time":0.6333,"name":"shikuai_4"},{"time":0.6667,"name":"shikuai_5"},{"time":0.7,"name":"shikuai_6"},{"time":0.7333,"name":"shikuai_7"},{"time":0.7667,"name":"shikuai_8"},{"time":0.8,"name":"shikuai_9"},{"time":0.8333,"name":"shikuai_10"},{"time":0.8667,"name":"shikuai_11"},{"time":0.9,"name":"shikuai_12"},{"time":0.9333,"name":"shikuai_13"},{"time":0.9667,"name":"shikuai_14"},{"time":1,"name":"shikuai_0"},{"time":1.0333,"name":"shikuai_1"},{"time":1.0667,"name":"shikuai_2"},{"time":1.1,"name":"shikuai_3"},{"time":1.1333,"name":"shikuai_4"},{"time":1.1667,"name":"shikuai_5"},{"time":1.2,"name":"shikuai_6"},{"time":1.2333,"name":"shikuai_7"},{"time":1.2667,"name":"shikuai_8"},{"time":1.3,"name":"shikuai_9"},{"time":1.3333,"name":"shikuai_10"},{"time":1.3667,"name":"shikuai_11"},{"time":1.4,"name":"shikuai_12"},{"time":1.4333,"name":"shikuai_13"},{"time":1.4667,"name":"shikuai_14"},{"time":1.5,"name":"shikuai_0"},{"time":1.5333,"name":"shikuai_1"},{"time":1.5667,"name":"shikuai_2"},{"time":1.6,"name":"shikuai_3"},{"time":1.6333,"name":"shikuai_4"},{"time":1.6667,"name":"shikuai_5"},{"time":1.7,"name":"shikuai_6"},{"time":1.7333,"name":"shikuai_7"},{"time":1.7667,"name":"shikuai_8"},{"time":1.8,"name":"shikuai_9"},{"time":1.8333,"name":"shikuai_10"},{"time":1.8667,"name":"shikuai_11"},{"time":1.9,"name":"shikuai_12"},{"time":1.9333,"name":"shikuai_13"},{"time":1.9667,"name":"shikuai_14"}]}},"bones":{"g2":{"rotate":[{"time":0,"angle":0},{"time":2,"angle":180}]},"2":{"scale":[{"time":0,"x":0.328,"y":0.29},{"time":0.2333,"x":0.597,"y":2.965},{"time":0.5,"x":1.066,"y":1.793}]},"shikuai2":{"scale":[{"time":0,"x":0.349,"y":0.349,"curve":[0.25,0,0.75,1]},{"time":0.1667,"x":1,"y":1}]},"g3":{"rotate":[{"time":0,"angle":0},{"time":2,"angle":180}]},"3":{"scale":[{"time":0,"x":0.328,"y":0.29},{"time":0.2333,"x":0.597,"y":2.965},{"time":0.5,"x":1.066,"y":1.793}]},"shikuai3":{"scale":[{"time":0,"x":0.349,"y":0.349,"curve":[0.25,0,0.75,1]},{"time":0.1667,"x":1,"y":1}]},"g4":{"rotate":[{"time":0,"angle":0},{"time":2,"angle":180}]},"5":{"scale":[{"time":0,"x":0.328,"y":0.29},{"time":0.2333,"x":0.597,"y":2.965},{"time":0.5,"x":1.066,"y":1.793}]},"shikuai4":{"scale":[{"time":0,"x":0.349,"y":0.349,"curve":[0.25,0,0.75,1]},{"time":0.1667,"x":1,"y":1}]}}}}}